paraflow/__init__.py
paraflow-0.0.1.dist-info/METADATA
paraflow-0.0.1.dist-info/WHEEL
paraflow-0.0.1.dist-info/top_level.txt
paraflow-0.0.1.dist-info/RECORD
