Metadata-Version: 2.4
Name: paraflow
Version: 0.0.1
Summary: under development
Author: Open Orion
License: MIT
Project-URL: Homepage, https://github.com/OpenOrion/paraflow
Project-URL: Repository, https://github.com/OpenOrion/paraflow
Classifier: Development Status :: 1 - Planning
Classifier: Intended Audience :: Developers
Classifier: License :: OSI Approved :: MIT License
Classifier: Programming Language :: Python :: 3
Classifier: Programming Language :: Python :: 3.8
Classifier: Programming Language :: Python :: 3.9
Classifier: Programming Language :: Python :: 3.10
Classifier: Programming Language :: Python :: 3.11
Classifier: Programming Language :: Python :: 3.12
Requires-Python: >=3.8
